mkdocs_towncrier/__init__.py
mkdocs_towncrier-0.1.5.dist-info/METADATA
mkdocs_towncrier-0.1.5.dist-info/WHEEL
mkdocs_towncrier-0.1.5.dist-info/entry_points.txt
mkdocs_towncrier-0.1.5.dist-info/licenses/LICENSE
mkdocs_towncrier-0.1.5.dist-info/RECORD
