Metadata-Version: 2.4
Name: mkdocs-towncrier
Version: 0.1.5
Summary: An insanely small plugin to add towncrier changelog draft into mkdocs
Project-URL: Repository, https://github.com/davfsa/mkdocs-towncrier
Project-URL: Issues, https://github.com/davfsa/mkdocs-towncrier/issues
Project-URL: CI, https://github.com/davfsa/mkdocs-towncrier/actions
Project-URL: Changelog, https://github.com/davfsa/mkdocs-towncrier/releases
License-File: LICENSE
Classifier: Development Status :: 5 - Production/Stable
Classifier: Environment :: Plugins
Classifier: Framework :: MkDocs
Classifier: Intended Audience :: Developers
Classifier: License :: OSI Approved :: MIT License
Classifier: Natural Language :: English
Classifier: Operating System :: OS Independent
Classifier: Programming Language :: Python :: 3.10
Classifier: Programming Language :: Python :: 3.11
Classifier: Programming Language :: Python :: 3.12
Classifier: Programming Language :: Python :: 3.13
Classifier: Programming Language :: Python :: Implementation :: CPython
Classifier: Typing :: Typed
Requires-Python: >=3.9
Requires-Dist: mkdocs<1.7.0,>=1.6.0
Requires-Dist: towncrier<26.0.0,>=24.7.0
